LICENSE
README.md
setup.cfg
setup.py
UML3/__init__.py
UML3.egg-info/PKG-INFO
UML3.egg-info/SOURCES.txt
UML3.egg-info/dependency_links.txt
UML3.egg-info/not-zip-safe
UML3.egg-info/requires.txt
UML3.egg-info/top_level.txt
UML3/MV/Matrix.py
UML3/MV/Vector.py
UML3/MV/__init__.py
UML3/MV/MV_error/Vector_error.py
UML3/MV/MV_error/__init__.py
UML3/MV/MV_error/msgs.py