Metadata-Version: 2.1
Name: UML3
Version: 0.0.1
Summary: provides a wide range of vector operations, including initialization, arithmetic operations, comparisons, geometric calculations, information retrieval, modification, iteration, index operations, mathematical operations, coordinate system transformations, vector operations, graphical representation, angle measurement conversion, serialization, and random vector generation.
Home-page: https://github.com/VIA-s-acc/UML3
Author: Via
Author-email: hroyango@my.msu.ru
License: GNU GPLv3
License-File: LICENSE
Requires-Dist: matplotlib
